jl95/pytools/envlib/vars/ssl/__init__.py
jl95terceira/pytools/envlib/vars/ssl/__init__.py
jl95terceira_pytools_env_ssl-0.1.3.dist-info/METADATA
jl95terceira_pytools_env_ssl-0.1.3.dist-info/WHEEL
jl95terceira_pytools_env_ssl-0.1.3.dist-info/RECORD
