Metadata-Version: 2.4
Name: jl95terceira_pytools_env_ssl
Version: 0.1.3
Summary: Environment variables collection - SSL
Project-URL: Homepage, https://github.com/jl95terceira/project-env-ssl
Project-URL: Issues, https://github.com/jl95terceira/project-env-ssl/issues
Author-email: Joao Luis Ornelas da Silva <jl95terceira@gmail.com>
Classifier: License :: OSI Approved :: MIT License
Classifier: Operating System :: OS Independent
Classifier: Programming Language :: Python :: 3
Requires-Python: >=3.12
Requires-Dist: jl95terceira-pytools-env>=0.2.7
